springboardvr/__init__.py
springboardvr/client.py
springboardvr/exceptions.py
springboardvr/sessions.py
springboardvr-0.1.0.dist-info/LICENSE
springboardvr-0.1.0.dist-info/METADATA
springboardvr-0.1.0.dist-info/WHEEL
springboardvr-0.1.0.dist-info/top_level.txt
springboardvr-0.1.0.dist-info/RECORD
